<?xml version="1.0" encoding="UTF-8"?>
<export version="D">
  <design>
    <source>C:\Users\pr3de\Documents\MASA\BLEANT Board\BLEANT\BLEANT.sch</source>
    <date>12/29/2019 12:44:47 PM</date>
    <tool>Eeschema (5.1.4)-1</tool>
    <sheet number="1" name="/" tstamps="/">
      <title_block>
        <title/>
        <company/>
        <rev/>
        <date/>
        <source>BLEANT.sch</source>
        <comment number="1" value=""/>
        <comment number="2" value=""/>
        <comment number="3" value=""/>
        <comment number="4" value=""/>
      </title_block>
    </sheet>
    <sheet number="2" name="/CAN_Template/" tstamps="/5E213D77/">
      <title_block>
        <title/>
        <company/>
        <rev/>
        <date/>
        <source>CAN_Template.sch</source>
        <comment number="1" value=""/>
        <comment number="2" value=""/>
        <comment number="3" value=""/>
        <comment number="4" value=""/>
      </title_block>
    </sheet>
  </design>
  <components>
    <comp ref="C7">
      <value>4.7uF</value>
      <footprint>Capacitor_SMD:C_0402_1005Metric</footprint>
      <datasheet>~</datasheet>
      <libsource lib="Device" part="C" description="Unpolarized capacitor"/>
      <sheetpath names="/" tstamps="/"/>
      <tstamp>5DF59304</tstamp>
    </comp>
    <comp ref="U1">
      <value>nRF51x22-QFxx</value>
      <footprint>Package_DFN_QFN:QFN-48-1EP_6x6mm_P0.4mm_EP4.6x4.6mm</footprint>
      <datasheet>http://infocenter.nordicsemi.com/pdf/nRF51822_PS_v3.3.pdf</datasheet>
      <libsource lib="MCU_Nordic" part="nRF51x22-QFxx" description="Multiprotocol BLE/2.4GHz Cortex-M0+ SoC"/>
      <sheetpath names="/" tstamps="/"/>
      <tstamp>5DF52931</tstamp>
    </comp>
    <comp ref="L4">
      <value>10uH</value>
      <footprint>Inductor_SMD:L_0603_1608Metric</footprint>
      <datasheet>~</datasheet>
      <libsource lib="Device" part="L" description="Inductor"/>
      <sheetpath names="/" tstamps="/"/>
      <tstamp>5DF61714</tstamp>
    </comp>
    <comp ref="L5">
      <value>15nH</value>
      <footprint>Inductor_SMD:L_0402_1005Metric</footprint>
      <datasheet>~</datasheet>
      <libsource lib="Device" part="L" description="Inductor"/>
      <sheetpath names="/" tstamps="/"/>
      <tstamp>5DF6252C</tstamp>
    </comp>
    <comp ref="C12">
      <value>1uF</value>
      <footprint>Capacitor_SMD:C_0402_1005Metric</footprint>
      <datasheet>~</datasheet>
      <libsource lib="Device" part="C" description="Unpolarized capacitor"/>
      <sheetpath names="/" tstamps="/"/>
      <tstamp>5DF62D8F</tstamp>
    </comp>
    <comp ref="C11">
      <value>100nF</value>
      <footprint>Capacitor_SMD:C_0402_1005Metric</footprint>
      <datasheet>~</datasheet>
      <libsource lib="Device" part="C" description="Unpolarized capacitor"/>
      <sheetpath names="/" tstamps="/"/>
      <tstamp>5DF66FC9</tstamp>
    </comp>
    <comp ref="C8">
      <value>100nF</value>
      <footprint>Capacitor_SMD:C_0402_1005Metric</footprint>
      <datasheet>~</datasheet>
      <libsource lib="Device" part="C" description="Unpolarized capacitor"/>
      <sheetpath names="/" tstamps="/"/>
      <tstamp>5DF71C46</tstamp>
    </comp>
    <comp ref="C10">
      <value>47nF</value>
      <footprint>Capacitor_SMD:C_0402_1005Metric</footprint>
      <datasheet>~</datasheet>
      <libsource lib="Device" part="C" description="Unpolarized capacitor"/>
      <sheetpath names="/" tstamps="/"/>
      <tstamp>5DF72D4E</tstamp>
    </comp>
    <comp ref="C9">
      <value>1nF</value>
      <footprint>Capacitor_SMD:C_0402_1005Metric</footprint>
      <datasheet>~</datasheet>
      <libsource lib="Device" part="C" description="Unpolarized capacitor"/>
      <sheetpath names="/" tstamps="/"/>
      <tstamp>5DF750C7</tstamp>
    </comp>
    <comp ref="C2">
      <value>12pF</value>
      <footprint>Capacitor_SMD:C_0402_1005Metric</footprint>
      <datasheet>~</datasheet>
      <libsource lib="Device" part="C" description="Unpolarized capacitor"/>
      <sheetpath names="/" tstamps="/"/>
      <tstamp>5DF8B53A</tstamp>
    </comp>
    <comp ref="C1">
      <value>12pF</value>
      <footprint>Capacitor_SMD:C_0402_1005Metric</footprint>
      <datasheet>~</datasheet>
      <libsource lib="Device" part="C" description="Unpolarized capacitor"/>
      <sheetpath names="/" tstamps="/"/>
      <tstamp>5DF8C639</tstamp>
    </comp>
    <comp ref="X2">
      <value>32.768kHz</value>
      <footprint>Crystal:Crystal_SMD_MicroCrystal_CC7V-T1A-2Pin_3.2x1.5mm</footprint>
      <datasheet>~</datasheet>
      <libsource lib="Device" part="Crystal" description="Two pin crystal"/>
      <sheetpath names="/" tstamps="/"/>
      <tstamp>5DF999FC</tstamp>
    </comp>
    <comp ref="C14">
      <value>20pF</value>
      <footprint>Capacitor_SMD:C_0402_1005Metric</footprint>
      <datasheet>~</datasheet>
      <libsource lib="Device" part="C" description="Unpolarized capacitor"/>
      <sheetpath names="/" tstamps="/"/>
      <tstamp>5DFAC68B</tstamp>
    </comp>
    <comp ref="C13">
      <value>20pF</value>
      <footprint>Capacitor_SMD:C_0402_1005Metric</footprint>
      <datasheet>~</datasheet>
      <libsource lib="Device" part="C" description="Unpolarized capacitor"/>
      <sheetpath names="/" tstamps="/"/>
      <tstamp>5DFAC691</tstamp>
    </comp>
    <comp ref="J1">
      <value>Conn_01x04_Male</value>
      <footprint>Connector_PinHeader_2.54mm:PinHeader_1x04_P2.54mm_Vertical</footprint>
      <datasheet>~</datasheet>
      <libsource lib="Connector" part="Conn_01x04_Male" description="Generic connector, single row, 01x04, script generated (kicad-library-utils/schlib/autogen/connector/)"/>
      <sheetpath names="/" tstamps="/"/>
      <tstamp>5DFB3EF7</tstamp>
    </comp>
    <comp ref="R2">
      <value>10k</value>
      <footprint>Resistor_SMD:R_0402_1005Metric</footprint>
      <datasheet>~</datasheet>
      <libsource lib="Device" part="R_US" description="Resistor, US symbol"/>
      <sheetpath names="/" tstamps="/"/>
      <tstamp>5DFC8910</tstamp>
    </comp>
    <comp ref="J2">
      <value>SC_19-20</value>
      <footprint>MASA_Library:Stack_Connector_2019_2020</footprint>
      <fields>
        <field name="Description">Conn Shrouded Header HDR 40 POS 1.27mm Solder ST SMD T/R</field>
        <field name="Height">11.35</field>
        <field name="Manufacturer_Name">SAMTEC</field>
        <field name="Manufacturer_Part_Number">TFC-120-32-F-D-A-K-TR</field>
      </fields>
      <libsource lib="MASA_Library" part="SC_19-20" description=""/>
      <sheetpath names="/" tstamps="/"/>
      <tstamp>5DFD9A87</tstamp>
    </comp>
    <comp ref="C19">
      <value>22uF</value>
      <footprint>Capacitor_SMD:C_0805_2012Metric</footprint>
      <datasheet>~</datasheet>
      <libsource lib="Device" part="C" description="Unpolarized capacitor"/>
      <sheetpath names="/" tstamps="/"/>
      <tstamp>5DFECE64</tstamp>
    </comp>
    <comp ref="C18">
      <value>10nF</value>
      <footprint>Capacitor_SMD:C_0402_1005Metric</footprint>
      <datasheet>~</datasheet>
      <libsource lib="Device" part="C" description="Unpolarized capacitor"/>
      <sheetpath names="/" tstamps="/"/>
      <tstamp>5DFECE6A</tstamp>
    </comp>
    <comp ref="L7">
      <value>4.7uH</value>
      <footprint>Inductor_SMD:L_0805_2012Metric</footprint>
      <datasheet>~</datasheet>
      <libsource lib="Device" part="L" description="Inductor"/>
      <sheetpath names="/" tstamps="/"/>
      <tstamp>5DFECE70</tstamp>
    </comp>
    <comp ref="U2">
      <value>LM50BIM3</value>
      <footprint>footprints:LM50_DBZ_3</footprint>
      <libsource lib="2019-12-19_22-46-35" part="LM50BIM3" description=""/>
      <sheetpath names="/" tstamps="/"/>
      <tstamp>5DFFA48C</tstamp>
    </comp>
    <comp ref="U3">
      <value>MP5077GG-Z</value>
      <footprint>MASA_Library:MP5077GG-Z</footprint>
      <libsource lib="MASA_Library" part="MP5077GG-Z" description=""/>
      <sheetpath names="/" tstamps="/"/>
      <tstamp>5DFF3D43</tstamp>
    </comp>
    <comp ref="R4">
      <value>820k</value>
      <footprint>Resistor_SMD:R_0402_1005Metric</footprint>
      <datasheet>~</datasheet>
      <libsource lib="Device" part="R_US" description="Resistor, US symbol"/>
      <sheetpath names="/" tstamps="/"/>
      <tstamp>5E009D99</tstamp>
    </comp>
    <comp ref="C21">
      <value>0.68uF</value>
      <footprint>Capacitor_SMD:C_0402_1005Metric</footprint>
      <datasheet>~</datasheet>
      <libsource lib="Device" part="C" description="Unpolarized capacitor"/>
      <sheetpath names="/" tstamps="/"/>
      <tstamp>5E00C19D</tstamp>
    </comp>
    <comp ref="U4">
      <value>MP5077GG-Z</value>
      <footprint>MASA_Library:MP5077GG-Z</footprint>
      <libsource lib="MASA_Library" part="MP5077GG-Z" description=""/>
      <sheetpath names="/" tstamps="/"/>
      <tstamp>5E0123EB</tstamp>
    </comp>
    <comp ref="R5">
      <value>820k</value>
      <footprint>Resistor_SMD:R_0402_1005Metric</footprint>
      <datasheet>~</datasheet>
      <libsource lib="Device" part="R_US" description="Resistor, US symbol"/>
      <sheetpath names="/" tstamps="/"/>
      <tstamp>5E0123F6</tstamp>
    </comp>
    <comp ref="C22">
      <value>1uF</value>
      <footprint>Capacitor_SMD:C_0402_1005Metric</footprint>
      <datasheet>~</datasheet>
      <libsource lib="Device" part="C" description="Unpolarized capacitor"/>
      <sheetpath names="/" tstamps="/"/>
      <tstamp>5E01240A</tstamp>
    </comp>
    <comp ref="R8">
      <value>3k</value>
      <footprint>Resistor_SMD:R_0402_1005Metric</footprint>
      <datasheet>~</datasheet>
      <libsource lib="Device" part="R_US" description="Resistor, US symbol"/>
      <sheetpath names="/" tstamps="/"/>
      <tstamp>5E056826</tstamp>
    </comp>
    <comp ref="J4">
      <value>Conn_01x02</value>
      <footprint>Connector_PinHeader_2.54mm:PinHeader_1x02_P2.54mm_Vertical</footprint>
      <datasheet>~</datasheet>
      <libsource lib="Connector_Generic" part="Conn_01x02" description="Generic connector, single row, 01x02, script generated (kicad-library-utils/schlib/autogen/connector/)"/>
      <sheetpath names="/" tstamps="/"/>
      <tstamp>5E063340</tstamp>
    </comp>
    <comp ref="J3">
      <value>Conn_01x02</value>
      <footprint>Connector_PinHeader_2.54mm:PinHeader_1x02_P2.54mm_Vertical</footprint>
      <datasheet>~</datasheet>
      <libsource lib="Connector_Generic" part="Conn_01x02" description="Generic connector, single row, 01x02, script generated (kicad-library-utils/schlib/autogen/connector/)"/>
      <sheetpath names="/" tstamps="/"/>
      <tstamp>5E072068</tstamp>
    </comp>
    <comp ref="R7">
      <value>1</value>
      <footprint>Resistor_SMD:R_0402_1005Metric</footprint>
      <datasheet>~</datasheet>
      <libsource lib="Device" part="R_US" description="Resistor, US symbol"/>
      <sheetpath names="/" tstamps="/"/>
      <tstamp>5E079EED</tstamp>
    </comp>
    <comp ref="IC1">
      <value>FAN4010IL6X_F113</value>
      <footprint>FAN4010:6-LEAD_MICROPAK</footprint>
      <datasheet>http://pdl.designspark.com/api/v1/manufacturers/53f31bb99b4759f8698ebd6d/part/54f601839b4759c27e8ce92c/54f601849b4759c27e8ce954/1pdf</datasheet>
      <fields>
        <field name="Description">Current Sense Amplifier Single Single Ended 6-Pin MLP</field>
        <field name="Manufacturer_Name">ON Semiconductor</field>
        <field name="Manufacturer_Part_Number">FAN4010IL6X_F113</field>
        <field name="Mouser Part Number">512-FAN4010IL6X_F113</field>
        <field name="Mouser Price/Stock">http://www.mouser.com/Search/ProductDetail.aspx?qs=bXpVsf6NmSLCEHlKPwERMg%3d%3d</field>
        <field name="RS Part Number">8650874P</field>
        <field name="RS Price/Stock">http://uk.rs-online.com/web/p/products/8650874P</field>
      </fields>
      <libsource lib="FAN4010IL6X_F113" part="FAN4010IL6X_F113" description="Current Sense Amplifier Single Single Ended 6-Pin MLP"/>
      <sheetpath names="/" tstamps="/"/>
      <tstamp>5E0293BC</tstamp>
    </comp>
    <comp ref="R9">
      <value>3k</value>
      <footprint>Resistor_SMD:R_0402_1005Metric</footprint>
      <datasheet>~</datasheet>
      <libsource lib="Device" part="R_US" description="Resistor, US symbol"/>
      <sheetpath names="/" tstamps="/"/>
      <tstamp>5E07C9A1</tstamp>
    </comp>
    <comp ref="IC2">
      <value>FAN4010IL6X_F113</value>
      <footprint>FAN4010:6-LEAD_MICROPAK</footprint>
      <datasheet>http://pdl.designspark.com/api/v1/manufacturers/53f31bb99b4759f8698ebd6d/part/54f601839b4759c27e8ce92c/54f601849b4759c27e8ce954/1pdf</datasheet>
      <fields>
        <field name="Description">Current Sense Amplifier Single Single Ended 6-Pin MLP</field>
        <field name="Manufacturer_Name">ON Semiconductor</field>
        <field name="Manufacturer_Part_Number">FAN4010IL6X_F113</field>
        <field name="Mouser Part Number">512-FAN4010IL6X_F113</field>
        <field name="Mouser Price/Stock">http://www.mouser.com/Search/ProductDetail.aspx?qs=bXpVsf6NmSLCEHlKPwERMg%3d%3d</field>
        <field name="RS Part Number">8650874P</field>
        <field name="RS Price/Stock">http://uk.rs-online.com/web/p/products/8650874P</field>
      </fields>
      <libsource lib="FAN4010IL6X_F113" part="FAN4010IL6X_F113" description="Current Sense Amplifier Single Single Ended 6-Pin MLP"/>
      <sheetpath names="/" tstamps="/"/>
      <tstamp>5E07C9D3</tstamp>
    </comp>
    <comp ref="Y1">
      <value>16MHz</value>
      <footprint>Crystal:Crystal_SMD_2520-4Pin_2.5x2.0mm</footprint>
      <datasheet>~</datasheet>
      <libsource lib="Device" part="Crystal_GND24" description="Four pin crystal, GND on pins 2 and 4"/>
      <sheetpath names="/" tstamps="/"/>
      <tstamp>5E090F8F</tstamp>
    </comp>
    <comp ref="C6">
      <value>1.5pF</value>
      <footprint>Capacitor_SMD:C_0402_1005Metric</footprint>
      <datasheet>~</datasheet>
      <libsource lib="Device" part="C" description="Unpolarized capacitor"/>
      <sheetpath names="/" tstamps="/"/>
      <tstamp>5DF837B8</tstamp>
    </comp>
    <comp ref="C4">
      <value>1pF</value>
      <footprint>Capacitor_SMD:C_0402_1005Metric</footprint>
      <datasheet>~</datasheet>
      <libsource lib="Device" part="C" description="Unpolarized capacitor"/>
      <sheetpath names="/" tstamps="/"/>
      <tstamp>5DF82C3E</tstamp>
    </comp>
    <comp ref="L3">
      <value>3.3nH</value>
      <footprint>Inductor_SMD:L_0402_1005Metric</footprint>
      <datasheet>~</datasheet>
      <libsource lib="Device" part="L" description="Inductor"/>
      <sheetpath names="/" tstamps="/"/>
      <tstamp>5DF82292</tstamp>
    </comp>
    <comp ref="C5">
      <value>2.2pF</value>
      <footprint>Capacitor_SMD:C_0402_1005Metric</footprint>
      <datasheet>~</datasheet>
      <libsource lib="Device" part="C" description="Unpolarized capacitor"/>
      <sheetpath names="/" tstamps="/"/>
      <tstamp>5DF7CB03</tstamp>
    </comp>
    <comp ref="L1">
      <value>4.7nH</value>
      <footprint>Inductor_SMD:L_0402_1005Metric</footprint>
      <datasheet>~</datasheet>
      <libsource lib="Device" part="L" description="Inductor"/>
      <sheetpath names="/" tstamps="/"/>
      <tstamp>5DF7C039</tstamp>
    </comp>
    <comp ref="L2">
      <value>10nH</value>
      <footprint>Inductor_SMD:L_0402_1005Metric</footprint>
      <datasheet>~</datasheet>
      <libsource lib="Device" part="L" description="Inductor"/>
      <sheetpath names="/" tstamps="/"/>
      <tstamp>5DF7B422</tstamp>
    </comp>
    <comp ref="C3">
      <value>2.2nF</value>
      <footprint>Capacitor_SMD:C_0402_1005Metric</footprint>
      <datasheet>~</datasheet>
      <libsource lib="Device" part="C" description="Unpolarized capacitor"/>
      <sheetpath names="/" tstamps="/"/>
      <tstamp>5DF7FAB1</tstamp>
    </comp>
    <comp ref="D3">
      <value>D_TVS</value>
      <footprint>Diode_SMD:D_SOD-523</footprint>
      <datasheet>~</datasheet>
      <libsource lib="Device" part="D_TVS" description="Bidirectional transient-voltage-suppression diode"/>
      <sheetpath names="/" tstamps="/"/>
      <tstamp>5E229A39</tstamp>
    </comp>
    <comp ref="J5">
      <value>1909763-1</value>
      <footprint>U:TE_1909763-1</footprint>
      <datasheet>https://www.te.com/usa-en/product-1909763-1.html?te_bu=Cor&amp;te_type=disp&amp;te_campaign=seda_glo_cor-seda-global-disp-prtnr-fy19-seda-model-bom-cta_sma-317_1&amp;elqCampaignId=32493</datasheet>
      <fields>
        <field name="Field4">1</field>
        <field name="Field5">1909763-1</field>
      </fields>
      <libsource lib="1909763-1" part="1909763-1" description=""/>
      <sheetpath names="/" tstamps="/"/>
      <tstamp>5E296787</tstamp>
    </comp>
    <comp ref="R1">
      <value>1</value>
      <footprint>Resistor_SMD:R_0402_1005Metric</footprint>
      <datasheet>~</datasheet>
      <libsource lib="Device" part="R_US" description="Resistor, US symbol"/>
      <sheetpath names="/" tstamps="/"/>
      <tstamp>5E2B4D00</tstamp>
    </comp>
    <comp ref="C16">
      <value>22uF</value>
      <footprint>Capacitor_SMD:C_0805_2012Metric</footprint>
      <datasheet>~</datasheet>
      <libsource lib="Device" part="C" description="Unpolarized capacitor"/>
      <sheetpath names="/" tstamps="/"/>
      <tstamp>5E2BA05E</tstamp>
    </comp>
    <comp ref="R6">
      <value>1</value>
      <footprint>Resistor_SMD:R_0402_1005Metric</footprint>
      <datasheet>~</datasheet>
      <libsource lib="Device" part="R_US" description="Resistor, US symbol"/>
      <sheetpath names="/" tstamps="/"/>
      <tstamp>5E2BA0A0</tstamp>
    </comp>
    <comp ref="C15">
      <value>10nF</value>
      <footprint>Capacitor_SMD:C_0402_1005Metric</footprint>
      <datasheet>~</datasheet>
      <libsource lib="Device" part="C" description="Unpolarized capacitor"/>
      <sheetpath names="/" tstamps="/"/>
      <tstamp>5E2BA068</tstamp>
    </comp>
    <comp ref="L9">
      <value>4.7uH</value>
      <footprint>Inductor_SMD:L_0805_2012Metric</footprint>
      <datasheet>~</datasheet>
      <libsource lib="Device" part="L" description="Inductor"/>
      <sheetpath names="/" tstamps="/"/>
      <tstamp>5E2BA072</tstamp>
    </comp>
    <comp ref="R3">
      <value>1</value>
      <footprint>Resistor_SMD:R_0402_1005Metric</footprint>
      <datasheet>~</datasheet>
      <libsource lib="Device" part="R_US" description="Resistor, US symbol"/>
      <sheetpath names="/" tstamps="/"/>
      <tstamp>5E2BA0B9</tstamp>
    </comp>
    <comp ref="D2">
      <value>D_TVS</value>
      <footprint>Diode_SMD:D_SOD-523</footprint>
      <datasheet>~</datasheet>
      <libsource lib="Device" part="D_TVS" description="Bidirectional transient-voltage-suppression diode"/>
      <sheetpath names="/" tstamps="/"/>
      <tstamp>5E2E6AA8</tstamp>
    </comp>
    <comp ref="R15">
      <value>6k</value>
      <footprint>Resistor_SMD:R_0402_1005Metric</footprint>
      <datasheet>~</datasheet>
      <libsource lib="Device" part="R_US" description="Resistor, US symbol"/>
      <sheetpath names="/" tstamps="/"/>
      <tstamp>5E08CFEF</tstamp>
    </comp>
    <comp ref="R14">
      <value>10k</value>
      <footprint>Resistor_SMD:R_0402_1005Metric</footprint>
      <datasheet>~</datasheet>
      <libsource lib="Device" part="R_US" description="Resistor, US symbol"/>
      <sheetpath names="/" tstamps="/"/>
      <tstamp>5E08E68C</tstamp>
    </comp>
    <comp ref="NP1">
      <value>60</value>
      <footprint>Resistor_SMD:R_0402_1005Metric</footprint>
      <datasheet>~</datasheet>
      <libsource lib="Device" part="R_US" description="Resistor, US symbol"/>
      <sheetpath names="/CAN_Template/" tstamps="/5E213D77/"/>
      <tstamp>5DCB3E43</tstamp>
    </comp>
    <comp ref="C23">
      <value>100pf</value>
      <footprint>Capacitor_SMD:C_0402_1005Metric</footprint>
      <datasheet>~</datasheet>
      <libsource lib="Device" part="C" description="Unpolarized capacitor"/>
      <sheetpath names="/CAN_Template/" tstamps="/5E213D77/"/>
      <tstamp>5DCB7D7B</tstamp>
    </comp>
    <comp ref="C25">
      <value>1nf</value>
      <footprint>Capacitor_SMD:C_0402_1005Metric</footprint>
      <datasheet>~</datasheet>
      <libsource lib="Device" part="C" description="Unpolarized capacitor"/>
      <sheetpath names="/CAN_Template/" tstamps="/5E213D77/"/>
      <tstamp>5DCB9CD1</tstamp>
    </comp>
    <comp ref="C26">
      <value>100nf</value>
      <footprint>Capacitor_SMD:C_0402_1005Metric</footprint>
      <datasheet>~</datasheet>
      <libsource lib="Device" part="C" description="Unpolarized capacitor"/>
      <sheetpath names="/CAN_Template/" tstamps="/5E213D77/"/>
      <tstamp>5DCBAD85</tstamp>
    </comp>
    <comp ref="C28">
      <value>100pf</value>
      <footprint>Capacitor_SMD:C_0402_1005Metric</footprint>
      <datasheet>~</datasheet>
      <libsource lib="Device" part="C" description="Unpolarized capacitor"/>
      <sheetpath names="/CAN_Template/" tstamps="/5E213D77/"/>
      <tstamp>5DCE6703</tstamp>
    </comp>
    <comp ref="NP2">
      <value>60</value>
      <footprint>Resistor_SMD:R_0402_1005Metric</footprint>
      <datasheet>~</datasheet>
      <libsource lib="Device" part="R_US" description="Resistor, US symbol"/>
      <sheetpath names="/CAN_Template/" tstamps="/5E213D77/"/>
      <tstamp>5DCE98D1</tstamp>
    </comp>
    <comp ref="C29">
      <value>1nf</value>
      <footprint>Capacitor_SMD:C_0402_1005Metric</footprint>
      <datasheet>~</datasheet>
      <libsource lib="Device" part="C" description="Unpolarized capacitor"/>
      <sheetpath names="/CAN_Template/" tstamps="/5E213D77/"/>
      <tstamp>5DCEFDFD</tstamp>
    </comp>
    <comp ref="R13">
      <value>0</value>
      <footprint>Resistor_SMD:R_0402_1005Metric</footprint>
      <datasheet>~</datasheet>
      <libsource lib="Device" part="R_US" description="Resistor, US symbol"/>
      <sheetpath names="/CAN_Template/" tstamps="/5E213D77/"/>
      <tstamp>5DCF1CE0</tstamp>
    </comp>
    <comp ref="D1">
      <value>D5V0L2B3W-7</value>
      <footprint>Package_TO_SOT_SMD:SOT-23</footprint>
      <datasheet>https://www.mouser.com/datasheet/2/115/D5V0L2B3W-218988.pdf</datasheet>
      <libsource lib="Device" part="D_TVS_x2_CAA" description="Bidirectional dual transient-voltage-suppression diode, center on pin 1"/>
      <sheetpath names="/CAN_Template/" tstamps="/5E213D77/"/>
      <tstamp>5DD0169A</tstamp>
    </comp>
    <comp ref="R12">
      <value>10k</value>
      <footprint>Resistor_SMD:R_0402_1005Metric</footprint>
      <datasheet>~</datasheet>
      <libsource lib="Device" part="R_US" description="Resistor, US symbol"/>
      <sheetpath names="/CAN_Template/" tstamps="/5E213D77/"/>
      <tstamp>5DD5BD7B</tstamp>
    </comp>
    <comp ref="R11">
      <value>0</value>
      <footprint>Resistor_SMD:R_0402_1005Metric</footprint>
      <datasheet>~</datasheet>
      <libsource lib="Device" part="R_US" description="Resistor, US symbol"/>
      <sheetpath names="/CAN_Template/" tstamps="/5E213D77/"/>
      <tstamp>5DD67335</tstamp>
    </comp>
    <comp ref="U5">
      <value>MCP2515-xSO</value>
      <footprint>Package_SO:SOIC-18W_7.5x11.6mm_P1.27mm</footprint>
      <datasheet>http://ww1.microchip.com/downloads/en/DeviceDoc/21801e.pdf</datasheet>
      <libsource lib="Interface_CAN_LIN" part="MCP2515-xSO" description="Stand-Alone CAN Controller with SPI Interface, SOIC-18"/>
      <sheetpath names="/CAN_Template/" tstamps="/5E213D77/"/>
      <tstamp>5DCB05B0</tstamp>
    </comp>
    <comp ref="C27">
      <value>100pf</value>
      <footprint>Capacitor_SMD:C_0402_1005Metric</footprint>
      <datasheet>~</datasheet>
      <libsource lib="Device" part="C" description="Unpolarized capacitor"/>
      <sheetpath names="/CAN_Template/" tstamps="/5E213D77/"/>
      <tstamp>5DCE5998</tstamp>
    </comp>
    <comp ref="U6">
      <value>SN65HVD1050D</value>
      <footprint>Package_SO:SOIC-8_3.9x4.9mm_P1.27mm</footprint>
      <datasheet>http://www.ti.com/lit/ds/symlink/sn65hvd1050.pdf</datasheet>
      <libsource lib="Interface_CAN_LIN" part="SN65HVD1050D" description="CAN Bus Transceiver, EMC optimised, 5.0V, 1Mbps, SOIC-8"/>
      <sheetpath names="/CAN_Template/" tstamps="/5E213D77/"/>
      <tstamp>5DD4ABBA</tstamp>
    </comp>
    <comp ref="R10">
      <value>0</value>
      <footprint>Resistor_SMD:R_0402_1005Metric</footprint>
      <datasheet>~</datasheet>
      <libsource lib="Device" part="R_US" description="Resistor, US symbol"/>
      <sheetpath names="/CAN_Template/" tstamps="/5E213D77/"/>
      <tstamp>5E0A7D89</tstamp>
    </comp>
    <comp ref="C20">
      <value>1nf</value>
      <footprint>Capacitor_SMD:C_0402_1005Metric</footprint>
      <datasheet>~</datasheet>
      <libsource lib="Device" part="C" description="Unpolarized capacitor"/>
      <sheetpath names="/CAN_Template/" tstamps="/5E213D77/"/>
      <tstamp>5E0BDAE5</tstamp>
    </comp>
    <comp ref="C17">
      <value>100nf</value>
      <footprint>Capacitor_SMD:C_0402_1005Metric</footprint>
      <datasheet>~</datasheet>
      <libsource lib="Device" part="C" description="Unpolarized capacitor"/>
      <sheetpath names="/CAN_Template/" tstamps="/5E213D77/"/>
      <tstamp>5E0BDAEB</tstamp>
    </comp>
    <comp ref="C24">
      <value>100pf</value>
      <footprint>Capacitor_SMD:C_0402_1005Metric</footprint>
      <datasheet>~</datasheet>
      <libsource lib="Device" part="C" description="Unpolarized capacitor"/>
      <sheetpath names="/CAN_Template/" tstamps="/5E213D77/"/>
      <tstamp>5E0C191D</tstamp>
    </comp>
  </components>
  <libparts>
    <libpart lib="1909763-1" part="1909763-1">
      <fields>
        <field name="Reference">J</field>
        <field name="Value">1909763-1</field>
        <field name="Footprint">TE_1909763-1</field>
        <field name="Datasheet">https://www.te.com/usa-en/product-1909763-1.html?te_bu=Cor&amp;te_type=disp&amp;te_campaign=seda_glo_cor-seda-global-disp-prtnr-fy19-seda-model-bom-cta_sma-317_1&amp;elqCampaignId=32493</field>
        <field name="Field4">1</field>
        <field name="Field5">1909763-1</field>
      </fields>
      <pins>
        <pin num="1" name="SIG" type="passive"/>
        <pin num="2" name="GND" type="passive"/>
        <pin num="3" name="GND" type="passive"/>
      </pins>
    </libpart>
    <libpart lib="2019-12-19_22-46-35" part="LM50BIM3">
      <footprints>
        <fp>MF03A</fp>
        <fp>MF03A-M</fp>
        <fp>MF03A-L</fp>
      </footprints>
      <fields>
        <field name="Reference">U</field>
        <field name="Value">LM50BIM3</field>
        <field name="Footprint">MF03A</field>
      </fields>
      <pins>
        <pin num="1" name="+VS" type="unspc"/>
        <pin num="2" name="VO" type="unspc"/>
        <pin num="3" name="GND" type="unspc"/>
      </pins>
    </libpart>
    <libpart lib="Connector" part="Conn_01x04_Male">
      <description>Generic connector, single row, 01x04, script generated (kicad-library-utils/schlib/autogen/connector/)</description>
      <docs>~</docs>
      <footprints>
        <fp>Connector*:*_1x??_*</fp>
      </footprints>
      <fields>
        <field name="Reference">J</field>
        <field name="Value">Conn_01x04_Male</field>
      </fields>
      <pins>
        <pin num="1" name="Pin_1" type="passive"/>
        <pin num="2" name="Pin_2" type="passive"/>
        <pin num="3" name="Pin_3" type="passive"/>
        <pin num="4" name="Pin_4" type="passive"/>
      </pins>
    </libpart>
    <libpart lib="Connector_Generic" part="Conn_01x02">
      <description>Generic connector, single row, 01x02, script generated (kicad-library-utils/schlib/autogen/connector/)</description>
      <docs>~</docs>
      <footprints>
        <fp>Connector*:*_1x??_*</fp>
      </footprints>
      <fields>
        <field name="Reference">J</field>
        <field name="Value">Conn_01x02</field>
      </fields>
      <pins>
        <pin num="1" name="Pin_1" type="passive"/>
        <pin num="2" name="Pin_2" type="passive"/>
      </pins>
    </libpart>
    <libpart lib="Device" part="C">
      <description>Unpolarized capacitor</description>
      <docs>~</docs>
      <footprints>
        <fp>C_*</fp>
      </footprints>
      <fields>
        <field name="Reference">C</field>
        <field name="Value">C</field>
      </fields>
      <pins>
        <pin num="1" name="~" type="passive"/>
        <pin num="2" name="~" type="passive"/>
      </pins>
    </libpart>
    <libpart lib="Device" part="Crystal">
      <description>Two pin crystal</description>
      <docs>~</docs>
      <footprints>
        <fp>Crystal*</fp>
      </footprints>
      <fields>
        <field name="Reference">Y</field>
        <field name="Value">Crystal</field>
      </fields>
      <pins>
        <pin num="1" name="1" type="passive"/>
        <pin num="2" name="2" type="passive"/>
      </pins>
    </libpart>
    <libpart lib="Device" part="Crystal_GND24">
      <description>Four pin crystal, GND on pins 2 and 4</description>
      <docs>~</docs>
      <footprints>
        <fp>Crystal*</fp>
      </footprints>
      <fields>
        <field name="Reference">Y</field>
        <field name="Value">Crystal_GND24</field>
      </fields>
      <pins>
        <pin num="1" name="1" type="passive"/>
        <pin num="2" name="2" type="passive"/>
        <pin num="3" name="3" type="passive"/>
        <pin num="4" name="4" type="passive"/>
      </pins>
    </libpart>
    <libpart lib="Device" part="D_TVS">
      <description>Bidirectional transient-voltage-suppression diode</description>
      <docs>~</docs>
      <footprints>
        <fp>TO-???*</fp>
        <fp>*_Diode_*</fp>
        <fp>*SingleDiode*</fp>
        <fp>D_*</fp>
      </footprints>
      <fields>
        <field name="Reference">D</field>
        <field name="Value">D_TVS</field>
      </fields>
      <pins>
        <pin num="1" name="A1" type="passive"/>
        <pin num="2" name="A2" type="passive"/>
      </pins>
    </libpart>
    <libpart lib="Device" part="D_TVS_x2_CAA">
      <description>Bidirectional dual transient-voltage-suppression diode, center on pin 1</description>
      <docs>~</docs>
      <fields>
        <field name="Reference">D</field>
        <field name="Value">D_TVS_x2_CAA</field>
      </fields>
      <pins>
        <pin num="1" name="common" type="input"/>
        <pin num="2" name="A1" type="passive"/>
        <pin num="3" name="A2" type="passive"/>
      </pins>
    </libpart>
    <libpart lib="Device" part="L">
      <description>Inductor</description>
      <docs>~</docs>
      <footprints>
        <fp>Choke_*</fp>
        <fp>*Coil*</fp>
        <fp>Inductor_*</fp>
        <fp>L_*</fp>
      </footprints>
      <fields>
        <field name="Reference">L</field>
        <field name="Value">L</field>
      </fields>
      <pins>
        <pin num="1" name="1" type="passive"/>
        <pin num="2" name="2" type="passive"/>
      </pins>
    </libpart>
    <libpart lib="Device" part="R_US">
      <description>Resistor, US symbol</description>
      <docs>~</docs>
      <footprints>
        <fp>R_*</fp>
      </footprints>
      <fields>
        <field name="Reference">R</field>
        <field name="Value">R_US</field>
      </fields>
      <pins>
        <pin num="1" name="~" type="passive"/>
        <pin num="2" name="~" type="passive"/>
      </pins>
    </libpart>
    <libpart lib="FAN4010IL6X_F113" part="FAN4010IL6X_F113">
      <description>Current Sense Amplifier Single Single Ended 6-Pin MLP</description>
      <docs>http://pdl.designspark.com/api/v1/manufacturers/53f31bb99b4759f8698ebd6d/part/54f601839b4759c27e8ce92c/54f601849b4759c27e8ce954/1pdf</docs>
      <fields>
        <field name="Reference">IC</field>
        <field name="Value">FAN4010IL6X_F113</field>
        <field name="Footprint">6-LEAD_MICROPAK</field>
        <field name="Datasheet">http://pdl.designspark.com/api/v1/manufacturers/53f31bb99b4759f8698ebd6d/part/54f601839b4759c27e8ce92c/54f601849b4759c27e8ce954/1pdf</field>
        <field name="Description">Current Sense Amplifier Single Single Ended 6-Pin MLP</field>
        <field name="Manufacturer_Name">ON Semiconductor</field>
        <field name="Manufacturer_Part_Number">FAN4010IL6X_F113</field>
        <field name="Mouser Part Number">512-FAN4010IL6X_F113</field>
        <field name="Mouser Price/Stock">http://www.mouser.com/Search/ProductDetail.aspx?qs=bXpVsf6NmSLCEHlKPwERMg%3d%3d</field>
        <field name="RS Part Number">8650874P</field>
        <field name="RS Price/Stock">http://uk.rs-online.com/web/p/products/8650874P</field>
      </fields>
      <pins>
        <pin num="1" name="VIN" type="unspc"/>
        <pin num="2" name="NC_1" type="unspc"/>
        <pin num="3" name="IOUT" type="unspc"/>
        <pin num="4" name="NC_2" type="unspc"/>
        <pin num="5" name="GND" type="unspc"/>
        <pin num="6" name="LOAD" type="unspc"/>
      </pins>
    </libpart>
    <libpart lib="Interface_CAN_LIN" part="MCP2515-xSO">
      <description>Stand-Alone CAN Controller with SPI Interface, SOIC-18</description>
      <docs>http://ww1.microchip.com/downloads/en/DeviceDoc/21801e.pdf</docs>
      <footprints>
        <fp>SOIC*7.5x11.6mm*P1.27mm*</fp>
      </footprints>
      <fields>
        <field name="Reference">U</field>
        <field name="Value">MCP2515-xSO</field>
        <field name="Footprint">Package_SO:SOIC-18W_7.5x11.6mm_P1.27mm</field>
      </fields>
      <pins>
        <pin num="1" name="TXCAN" type="output"/>
        <pin num="2" name="RXCAN" type="input"/>
        <pin num="3" name="CLKOUT/SOF" type="output"/>
        <pin num="4" name="~TX0RTS" type="input"/>
        <pin num="5" name="~TX1RTS" type="input"/>
        <pin num="6" name="~TX2RTS" type="input"/>
        <pin num="7" name="OSC2" type="output"/>
        <pin num="8" name="OSC1" type="input"/>
        <pin num="9" name="VSS" type="power_in"/>
        <pin num="10" name="~RX1BF" type="output"/>
        <pin num="11" name="~RX0BF" type="output"/>
        <pin num="12" name="~INT" type="output"/>
        <pin num="13" name="SCK" type="input"/>
        <pin num="14" name="SI" type="input"/>
        <pin num="15" name="SO" type="output"/>
        <pin num="16" name="~CS" type="input"/>
        <pin num="17" name="~RESET" type="input"/>
        <pin num="18" name="VDD" type="power_in"/>
      </pins>
    </libpart>
    <libpart lib="Interface_CAN_LIN" part="SN65HVD1050D">
      <description>CAN Bus Transceiver, EMC optimised, 5.0V, 1Mbps, SOIC-8</description>
      <docs>http://www.ti.com/lit/ds/symlink/sn65hvd1050.pdf</docs>
      <footprints>
        <fp>SOIC*3.9x4.9mm*P1.27mm*</fp>
      </footprints>
      <fields>
        <field name="Reference">U</field>
        <field name="Value">SN65HVD1050D</field>
        <field name="Footprint">Package_SO:SOIC-8_3.9x4.9mm_P1.27mm</field>
      </fields>
      <pins>
        <pin num="1" name="TXD" type="input"/>
        <pin num="2" name="GND" type="power_in"/>
        <pin num="3" name="VCC" type="power_in"/>
        <pin num="4" name="RXD" type="output"/>
        <pin num="5" name="VREF" type="passive"/>
        <pin num="6" name="CANL" type="BiDi"/>
        <pin num="7" name="CANH" type="BiDi"/>
        <pin num="8" name="S" type="input"/>
      </pins>
    </libpart>
    <libpart lib="MASA_Library" part="MP5077GG-Z">
      <fields>
        <field name="Reference">U</field>
        <field name="Value">MP5077GG-Z</field>
        <field name="Footprint">MASA_Library:MP5077GG-Z</field>
      </fields>
      <pins>
        <pin num="1" name="EN" type="input"/>
        <pin num="2" name="GND" type="input"/>
        <pin num="3" name="Vcc" type="input"/>
        <pin num="4" name="Ilim" type="output"/>
        <pin num="5" name="SS" type="output"/>
        <pin num="6" name="Vin" type="input"/>
        <pin num="7" name="Vout" type="output"/>
        <pin num="8" name="Vout" type="output"/>
        <pin num="9" name="Vout" type="output"/>
        <pin num="10" name="Vout" type="output"/>
        <pin num="11" name="Vin" type="input"/>
      </pins>
    </libpart>
    <libpart lib="MASA_Library" part="SC_19-20">
      <fields>
        <field name="Reference">J</field>
        <field name="Value">SC_19-20</field>
        <field name="Footprint">MASA_Library:Stack_Connector_2019_2020</field>
        <field name="Description">Conn Shrouded Header HDR 40 POS 1.27mm Solder ST SMD T/R</field>
        <field name="Height">11.35</field>
        <field name="Manufacturer_Name">SAMTEC</field>
        <field name="Manufacturer_Part_Number">TFC-120-32-F-D-A-K-TR</field>
      </fields>
      <pins>
        <pin num="1" name="GND" type="unspc"/>
        <pin num="2" name="3V3" type="unspc"/>
        <pin num="3" name="3V3" type="unspc"/>
        <pin num="4" name="GND" type="unspc"/>
        <pin num="5" name="GND" type="unspc"/>
        <pin num="6" name="3V3" type="unspc"/>
        <pin num="7" name="3V3" type="unspc"/>
        <pin num="8" name="SENSE" type="unspc"/>
        <pin num="9" name="9" type="unspc"/>
        <pin num="10" name="10" type="unspc"/>
        <pin num="11" name="11" type="unspc"/>
        <pin num="12" name="12" type="unspc"/>
        <pin num="13" name="13" type="unspc"/>
        <pin num="14" name="14" type="unspc"/>
        <pin num="15" name="15" type="unspc"/>
        <pin num="16" name="16" type="unspc"/>
        <pin num="17" name="17" type="unspc"/>
        <pin num="18" name="18" type="unspc"/>
        <pin num="19" name="GND" type="unspc"/>
        <pin num="20" name="GND" type="unspc"/>
        <pin num="21" name="CAN_H" type="unspc"/>
        <pin num="22" name="22" type="unspc"/>
        <pin num="23" name="CAN_L" type="unspc"/>
        <pin num="24" name="24" type="unspc"/>
        <pin num="25" name="UART1_TX" type="unspc"/>
        <pin num="26" name="26" type="unspc"/>
        <pin num="27" name="UART1_RX" type="unspc"/>
        <pin num="28" name="28" type="unspc"/>
        <pin num="29" name="UART2_TX" type="unspc"/>
        <pin num="30" name="30" type="unspc"/>
        <pin num="31" name="UART2_RX" type="unspc"/>
        <pin num="32" name="32" type="unspc"/>
        <pin num="33" name="33" type="unspc"/>
        <pin num="34" name="5V0" type="unspc"/>
        <pin num="35" name="5V0" type="unspc"/>
        <pin num="36" name="GND" type="unspc"/>
        <pin num="37" name="GND" type="unspc"/>
        <pin num="38" name="5V0" type="unspc"/>
        <pin num="39" name="5V0" type="unspc"/>
        <pin num="40" name="GND" type="unspc"/>
      </pins>
    </libpart>
    <libpart lib="MCU_Nordic" part="nRF51x22-QFxx">
      <description>Multiprotocol BLE/2.4GHz Cortex-M0+ SoC</description>
      <docs>http://infocenter.nordicsemi.com/pdf/nRF51822_PS_v3.3.pdf</docs>
      <footprints>
        <fp>QFN*1EP*6x6mm*P0.4mm*</fp>
      </footprints>
      <fields>
        <field name="Reference">U</field>
        <field name="Value">nRF51x22-QFxx</field>
        <field name="Footprint">Package_DFN_QFN:QFN-48-1EP_6x6mm_P0.4mm_EP4.6x4.6mm</field>
      </fields>
      <pins>
        <pin num="1" name="VDD" type="power_in"/>
        <pin num="2" name="DCC" type="power_out"/>
        <pin num="3" name="P0.30" type="BiDi"/>
        <pin num="4" name="P0.0" type="BiDi"/>
        <pin num="5" name="P0.1" type="BiDi"/>
        <pin num="6" name="P0.2" type="BiDi"/>
        <pin num="7" name="P0.3" type="BiDi"/>
        <pin num="8" name="P0.4" type="BiDi"/>
        <pin num="9" name="P0.5" type="BiDi"/>
        <pin num="10" name="P0.6" type="BiDi"/>
        <pin num="11" name="P0.7" type="BiDi"/>
        <pin num="12" name="VDD" type="passive"/>
        <pin num="13" name="VSS" type="power_in"/>
        <pin num="14" name="P0.8" type="BiDi"/>
        <pin num="15" name="P0.9" type="BiDi"/>
        <pin num="16" name="P0.10" type="BiDi"/>
        <pin num="17" name="P0.11" type="BiDi"/>
        <pin num="18" name="P0.12" type="BiDi"/>
        <pin num="19" name="P0.13" type="BiDi"/>
        <pin num="20" name="P0.14" type="BiDi"/>
        <pin num="21" name="P0.15" type="BiDi"/>
        <pin num="22" name="P0.16" type="BiDi"/>
        <pin num="23" name="SWDIO/~RST" type="BiDi"/>
        <pin num="24" name="SWDCLK" type="input"/>
        <pin num="25" name="P0.17" type="BiDi"/>
        <pin num="26" name="P0.18" type="BiDi"/>
        <pin num="27" name="P0.19" type="BiDi"/>
        <pin num="28" name="P0.20" type="BiDi"/>
        <pin num="29" name="DEC2" type="passive"/>
        <pin num="30" name="VDD_PA" type="power_out"/>
        <pin num="31" name="ANT1" type="output"/>
        <pin num="32" name="ANT2" type="output"/>
        <pin num="33" name="VSS" type="passive"/>
        <pin num="34" name="VSS" type="passive"/>
        <pin num="35" name="AVDD" type="power_in"/>
        <pin num="36" name="AVDD" type="passive"/>
        <pin num="37" name="XC1" type="input"/>
        <pin num="38" name="XC2" type="input"/>
        <pin num="39" name="DEC1" type="passive"/>
        <pin num="40" name="P0.21" type="BiDi"/>
        <pin num="41" name="P0.22" type="BiDi"/>
        <pin num="42" name="P0.23" type="BiDi"/>
        <pin num="43" name="P0.24" type="BiDi"/>
        <pin num="44" name="P0.25" type="BiDi"/>
        <pin num="45" name="P0.26" type="BiDi"/>
        <pin num="46" name="P0.27" type="BiDi"/>
        <pin num="47" name="P0.28" type="BiDi"/>
        <pin num="48" name="P0.29" type="BiDi"/>
        <pin num="49" name="EP" type="power_in"/>
      </pins>
    </libpart>
  </libparts>
  <libraries>
    <library logical="1909763-1">
      <uri>C:/Users/pr3de/Documents/MASA/BLEANT Board/U.FL/1909763-1.lib</uri>
    </library>
    <library logical="2019-12-19_22-46-35">
      <uri>C:/Users/pr3de/Documents/MASA/BLEANT Board/2019-12-20_19-01-00/symbols.lib</uri>
    </library>
    <library logical="Connector">
      <uri>C:\Program Files\KiCad\share\kicad\library/Connector.lib</uri>
    </library>
    <library logical="Connector_Generic">
      <uri>C:\Program Files\KiCad\share\kicad\library/Connector_Generic.lib</uri>
    </library>
    <library logical="Device">
      <uri>C:\Program Files\KiCad\share\kicad\library/Device.lib</uri>
    </library>
    <library logical="FAN4010IL6X_F113">
      <uri>C:/Users/pr3de/Documents/MASA/MASA_Library/FAN4010IL6X_F113.lib</uri>
    </library>
    <library logical="Interface_CAN_LIN">
      <uri>C:\Program Files\KiCad\share\kicad\library/Interface_CAN_LIN.lib</uri>
    </library>
    <library logical="MASA_Library">
      <uri>C:/Users/pr3de/Documents/MASA/MASA_Library/MASA_Library.lib</uri>
    </library>
    <library logical="MCU_Nordic">
      <uri>C:\Program Files\KiCad\share\kicad\library/MCU_Nordic.lib</uri>
    </library>
  </libraries>
  <nets>
    <net code="1" name="GND">
      <node ref="R3" pin="2"/>
      <node ref="J2" pin="1"/>
      <node ref="R14" pin="2"/>
      <node ref="C18" pin="2"/>
      <node ref="U2" pin="3"/>
      <node ref="U3" pin="2"/>
      <node ref="J2" pin="40"/>
      <node ref="J2" pin="5"/>
      <node ref="J2" pin="20"/>
      <node ref="C24" pin="1"/>
      <node ref="R8" pin="2"/>
      <node ref="C17" pin="2"/>
      <node ref="C20" pin="1"/>
      <node ref="J2" pin="19"/>
      <node ref="J2" pin="37"/>
      <node ref="J2" pin="4"/>
      <node ref="D2" pin="2"/>
      <node ref="J1" pin="3"/>
      <node ref="R1" pin="2"/>
      <node ref="J5" pin="3"/>
      <node ref="J5" pin="2"/>
      <node ref="C14" pin="2"/>
      <node ref="C9" pin="1"/>
      <node ref="C13" pin="2"/>
      <node ref="C10" pin="2"/>
      <node ref="C8" pin="2"/>
      <node ref="C11" pin="2"/>
      <node ref="D3" pin="2"/>
      <node ref="U1" pin="33"/>
      <node ref="U1" pin="34"/>
      <node ref="U1" pin="49"/>
      <node ref="J2" pin="36"/>
      <node ref="C3" pin="1"/>
      <node ref="C7" pin="2"/>
      <node ref="C15" pin="2"/>
      <node ref="U1" pin="13"/>
      <node ref="C2" pin="2"/>
      <node ref="C1" pin="2"/>
      <node ref="C12" pin="1"/>
      <node ref="R9" pin="2"/>
      <node ref="C4" pin="2"/>
      <node ref="C6" pin="2"/>
      <node ref="C22" pin="1"/>
      <node ref="R5" pin="1"/>
      <node ref="C29" pin="2"/>
      <node ref="U4" pin="2"/>
      <node ref="U6" pin="2"/>
      <node ref="C27" pin="1"/>
      <node ref="U5" pin="18"/>
      <node ref="C28" pin="1"/>
      <node ref="Y1" pin="4"/>
      <node ref="Y1" pin="2"/>
      <node ref="C26" pin="2"/>
      <node ref="C23" pin="2"/>
      <node ref="C25" pin="1"/>
      <node ref="R12" pin="2"/>
      <node ref="IC2" pin="5"/>
      <node ref="D1" pin="1"/>
      <node ref="C21" pin="1"/>
      <node ref="IC1" pin="5"/>
      <node ref="R4" pin="1"/>
    </net>
    <net code="2" name="Net-(IC2-Pad4)">
      <node ref="IC2" pin="4"/>
    </net>
    <net code="3" name="5V0Sense">
      <node ref="U1" pin="6"/>
      <node ref="R9" pin="1"/>
      <node ref="IC2" pin="3"/>
    </net>
    <net code="4" name="Net-(IC2-Pad2)">
      <node ref="IC2" pin="2"/>
    </net>
    <net code="5" name="Net-(L1-Pad1)">
      <node ref="L2" pin="2"/>
      <node ref="L1" pin="1"/>
      <node ref="U1" pin="31"/>
    </net>
    <net code="6" name="VDD_PA">
      <node ref="C3" pin="2"/>
      <node ref="U1" pin="30"/>
      <node ref="L2" pin="1"/>
    </net>
    <net code="7" name="Net-(C5-Pad1)">
      <node ref="L1" pin="2"/>
      <node ref="U1" pin="32"/>
      <node ref="C5" pin="1"/>
    </net>
    <net code="8" name="Net-(C4-Pad1)">
      <node ref="C5" pin="2"/>
      <node ref="C4" pin="1"/>
      <node ref="L3" pin="2"/>
    </net>
    <net code="9" name="Net-(C6-Pad1)">
      <node ref="C6" pin="1"/>
      <node ref="L3" pin="1"/>
      <node ref="J5" pin="1"/>
    </net>
    <net code="10" name="Net-(C22-Pad2)">
      <node ref="C22" pin="2"/>
      <node ref="U4" pin="5"/>
    </net>
    <net code="11" name="Net-(R5-Pad2)">
      <node ref="R5" pin="2"/>
      <node ref="U4" pin="4"/>
    </net>
    <net code="12" name="5V0">
      <node ref="U3" pin="3"/>
      <node ref="J2" pin="34"/>
      <node ref="J2" pin="35"/>
      <node ref="U3" pin="1"/>
      <node ref="U4" pin="6"/>
      <node ref="U4" pin="3"/>
      <node ref="J2" pin="39"/>
      <node ref="J2" pin="38"/>
      <node ref="U4" pin="1"/>
      <node ref="J3" pin="2"/>
      <node ref="U4" pin="11"/>
    </net>
    <net code="13" name="Net-(C21-Pad2)">
      <node ref="C21" pin="2"/>
      <node ref="U3" pin="5"/>
    </net>
    <net code="14" name="Net-(R4-Pad2)">
      <node ref="U3" pin="4"/>
      <node ref="R4" pin="2"/>
    </net>
    <net code="15" name="+3V3">
      <node ref="R2" pin="1"/>
      <node ref="U1" pin="12"/>
      <node ref="J1" pin="4"/>
      <node ref="U1" pin="10"/>
      <node ref="U1" pin="1"/>
      <node ref="C7" pin="1"/>
      <node ref="C11" pin="1"/>
      <node ref="R6" pin="1"/>
      <node ref="IC1" pin="6"/>
    </net>
    <net code="16" name="Net-(IC1-Pad4)">
      <node ref="IC1" pin="4"/>
    </net>
    <net code="17" name="3V3Sense">
      <node ref="R8" pin="1"/>
      <node ref="U1" pin="7"/>
      <node ref="IC1" pin="3"/>
    </net>
    <net code="18" name="Net-(IC1-Pad2)">
      <node ref="IC1" pin="2"/>
    </net>
    <net code="19" name="Net-(C16-Pad1)">
      <node ref="C16" pin="1"/>
      <node ref="IC1" pin="1"/>
      <node ref="R6" pin="2"/>
      <node ref="L9" pin="2"/>
    </net>
    <net code="20" name="3V3">
      <node ref="J4" pin="2"/>
      <node ref="J2" pin="7"/>
      <node ref="J2" pin="3"/>
      <node ref="J2" pin="6"/>
      <node ref="J2" pin="2"/>
      <node ref="U3" pin="11"/>
      <node ref="U3" pin="6"/>
    </net>
    <net code="21" name="+5V">
      <node ref="C20" pin="2"/>
      <node ref="C17" pin="1"/>
      <node ref="R15" pin="1"/>
      <node ref="U2" pin="1"/>
      <node ref="R7" pin="1"/>
      <node ref="IC2" pin="6"/>
      <node ref="U6" pin="3"/>
      <node ref="U5" pin="9"/>
      <node ref="C25" pin="2"/>
      <node ref="C26" pin="1"/>
    </net>
    <net code="22" name="Net-(C16-Pad2)">
      <node ref="R3" pin="1"/>
      <node ref="C16" pin="2"/>
    </net>
    <net code="23" name="Net-(C15-Pad1)">
      <node ref="U3" pin="10"/>
      <node ref="J4" pin="1"/>
      <node ref="U3" pin="8"/>
      <node ref="D2" pin="1"/>
      <node ref="U3" pin="7"/>
      <node ref="U3" pin="9"/>
      <node ref="C15" pin="1"/>
      <node ref="L9" pin="1"/>
    </net>
    <net code="24" name="Net-(R14-Pad1)">
      <node ref="R15" pin="2"/>
      <node ref="U1" pin="5"/>
      <node ref="R14" pin="1"/>
    </net>
    <net code="25" name="SCK">
      <node ref="U5" pin="13"/>
      <node ref="U1" pin="21"/>
    </net>
    <net code="26" name="Net-(C18-Pad1)">
      <node ref="L7" pin="1"/>
      <node ref="J3" pin="1"/>
      <node ref="D3" pin="1"/>
      <node ref="C18" pin="1"/>
      <node ref="U4" pin="7"/>
      <node ref="U4" pin="8"/>
      <node ref="U4" pin="10"/>
      <node ref="U4" pin="9"/>
    </net>
    <net code="27" name="CAN_RST">
      <node ref="U1" pin="17"/>
      <node ref="U5" pin="17"/>
    </net>
    <net code="28" name="RX0BF">
      <node ref="U1" pin="25"/>
      <node ref="U5" pin="11"/>
    </net>
    <net code="29" name="CAN_INT">
      <node ref="U1" pin="22"/>
      <node ref="U5" pin="12"/>
    </net>
    <net code="30" name="CS">
      <node ref="U5" pin="16"/>
      <node ref="U1" pin="18"/>
    </net>
    <net code="31" name="MISO">
      <node ref="U5" pin="15"/>
      <node ref="U1" pin="19"/>
    </net>
    <net code="32" name="MOSI">
      <node ref="U5" pin="14"/>
      <node ref="U1" pin="20"/>
    </net>
    <net code="33" name="CAN_H">
      <node ref="D1" pin="3"/>
      <node ref="NP1" pin="1"/>
      <node ref="C27" pin="2"/>
      <node ref="J2" pin="21"/>
      <node ref="U6" pin="7"/>
    </net>
    <net code="34" name="CAN_L">
      <node ref="U6" pin="6"/>
      <node ref="D1" pin="2"/>
      <node ref="C28" pin="2"/>
      <node ref="NP2" pin="2"/>
      <node ref="J2" pin="23"/>
    </net>
    <net code="36" name="Net-(C19-Pad2)">
      <node ref="C19" pin="2"/>
      <node ref="R1" pin="1"/>
    </net>
    <net code="37" name="Net-(C10-Pad1)">
      <node ref="C10" pin="1"/>
      <node ref="U1" pin="29"/>
    </net>
    <net code="38" name="Net-(C8-Pad1)">
      <node ref="C8" pin="1"/>
      <node ref="U1" pin="39"/>
    </net>
    <net code="39" name="Net-(C12-Pad2)">
      <node ref="L5" pin="1"/>
      <node ref="C12" pin="2"/>
      <node ref="U1" pin="35"/>
      <node ref="U1" pin="36"/>
      <node ref="C9" pin="2"/>
    </net>
    <net code="40" name="Net-(C2-Pad1)">
      <node ref="U1" pin="38"/>
      <node ref="Y1" pin="3"/>
      <node ref="C2" pin="1"/>
    </net>
    <net code="41" name="Net-(C1-Pad1)">
      <node ref="U1" pin="37"/>
      <node ref="Y1" pin="1"/>
      <node ref="C1" pin="1"/>
    </net>
    <net code="42" name="Net-(U1-Pad3)">
      <node ref="U1" pin="3"/>
    </net>
    <net code="43" name="Net-(U1-Pad28)">
      <node ref="U1" pin="28"/>
    </net>
    <net code="44" name="Net-(U1-Pad27)">
      <node ref="U1" pin="27"/>
    </net>
    <net code="45" name="RX1BF">
      <node ref="U1" pin="26"/>
      <node ref="U5" pin="10"/>
    </net>
    <net code="46" name="Net-(L4-Pad2)">
      <node ref="U1" pin="2"/>
      <node ref="L4" pin="2"/>
    </net>
    <net code="47" name="TX2RTS">
      <node ref="U1" pin="16"/>
      <node ref="U5" pin="6"/>
    </net>
    <net code="48" name="TX1RTS">
      <node ref="U1" pin="15"/>
      <node ref="U5" pin="5"/>
    </net>
    <net code="49" name="TX0RTS">
      <node ref="U5" pin="4"/>
      <node ref="U1" pin="14"/>
    </net>
    <net code="50" name="Net-(U1-Pad11)">
      <node ref="U1" pin="11"/>
    </net>
    <net code="51" name="XL1">
      <node ref="X2" pin="1"/>
      <node ref="C13" pin="1"/>
      <node ref="U1" pin="46"/>
    </net>
    <net code="52" name="Net-(L4-Pad1)">
      <node ref="L4" pin="1"/>
      <node ref="L5" pin="2"/>
    </net>
    <net code="53" name="Temperature">
      <node ref="U1" pin="9"/>
      <node ref="U2" pin="2"/>
    </net>
    <net code="54" name="Net-(U1-Pad8)">
      <node ref="U1" pin="8"/>
    </net>
    <net code="55" name="UART_TX">
      <node ref="J2" pin="29"/>
      <node ref="U1" pin="48"/>
    </net>
    <net code="56" name="UART_RX">
      <node ref="U1" pin="47"/>
      <node ref="J2" pin="31"/>
    </net>
    <net code="57" name="XL2">
      <node ref="X2" pin="2"/>
      <node ref="U1" pin="45"/>
      <node ref="C14" pin="1"/>
    </net>
    <net code="58" name="Net-(U1-Pad44)">
      <node ref="U1" pin="44"/>
    </net>
    <net code="59" name="Net-(U1-Pad43)">
      <node ref="U1" pin="43"/>
    </net>
    <net code="60" name="Net-(U1-Pad42)">
      <node ref="U1" pin="42"/>
    </net>
    <net code="61" name="Net-(U1-Pad41)">
      <node ref="U1" pin="41"/>
    </net>
    <net code="62" name="Net-(U1-Pad40)">
      <node ref="U1" pin="40"/>
    </net>
    <net code="63" name="Net-(U1-Pad4)">
      <node ref="U1" pin="4"/>
    </net>
    <net code="64" name="Net-(C19-Pad1)">
      <node ref="IC2" pin="1"/>
      <node ref="L7" pin="2"/>
      <node ref="C19" pin="1"/>
      <node ref="R7" pin="2"/>
    </net>
    <net code="65" name="Net-(J2-Pad9)">
      <node ref="J2" pin="9"/>
    </net>
    <net code="66" name="Net-(J2-Pad8)">
      <node ref="J2" pin="8"/>
    </net>
    <net code="67" name="Net-(J2-Pad11)">
      <node ref="J2" pin="11"/>
    </net>
    <net code="68" name="Net-(J2-Pad10)">
      <node ref="J2" pin="10"/>
    </net>
    <net code="69" name="SWDIO">
      <node ref="U1" pin="23"/>
      <node ref="J1" pin="2"/>
      <node ref="R2" pin="2"/>
    </net>
    <net code="70" name="SWDCLK">
      <node ref="J1" pin="1"/>
      <node ref="U1" pin="24"/>
    </net>
    <net code="71" name="Net-(J2-Pad13)">
      <node ref="J2" pin="13"/>
    </net>
    <net code="72" name="Net-(J2-Pad12)">
      <node ref="J2" pin="12"/>
    </net>
    <net code="73" name="Net-(J2-Pad33)">
      <node ref="J2" pin="33"/>
    </net>
    <net code="74" name="Net-(J2-Pad32)">
      <node ref="J2" pin="32"/>
    </net>
    <net code="75" name="Net-(J2-Pad30)">
      <node ref="J2" pin="30"/>
    </net>
    <net code="76" name="Net-(J2-Pad28)">
      <node ref="J2" pin="28"/>
    </net>
    <net code="77" name="Net-(J2-Pad27)">
      <node ref="J2" pin="27"/>
    </net>
    <net code="78" name="Net-(J2-Pad25)">
      <node ref="J2" pin="25"/>
    </net>
    <net code="79" name="Net-(J2-Pad26)">
      <node ref="J2" pin="26"/>
    </net>
    <net code="80" name="Net-(J2-Pad14)">
      <node ref="J2" pin="14"/>
    </net>
    <net code="81" name="Net-(J2-Pad15)">
      <node ref="J2" pin="15"/>
    </net>
    <net code="82" name="Net-(J2-Pad16)">
      <node ref="J2" pin="16"/>
    </net>
    <net code="83" name="Net-(J2-Pad17)">
      <node ref="J2" pin="17"/>
    </net>
    <net code="84" name="Net-(J2-Pad18)">
      <node ref="J2" pin="18"/>
    </net>
    <net code="85" name="Net-(J2-Pad22)">
      <node ref="J2" pin="22"/>
    </net>
    <net code="86" name="Net-(J2-Pad24)">
      <node ref="J2" pin="24"/>
    </net>
    <net code="87" name="Net-(C24-Pad2)">
      <node ref="R11" pin="1"/>
      <node ref="C24" pin="2"/>
      <node ref="U6" pin="1"/>
    </net>
    <net code="88" name="Net-(R12-Pad1)">
      <node ref="R12" pin="1"/>
      <node ref="U6" pin="8"/>
    </net>
    <net code="89" name="Net-(R10-Pad2)">
      <node ref="U6" pin="4"/>
      <node ref="R10" pin="2"/>
    </net>
    <net code="90" name="Net-(U5-Pad3)">
      <node ref="U5" pin="3"/>
    </net>
    <net code="94" name="Net-(R11-Pad2)">
      <node ref="R11" pin="2"/>
      <node ref="U5" pin="1"/>
    </net>
    <net code="95" name="Net-(C23-Pad1)">
      <node ref="C23" pin="1"/>
      <node ref="R10" pin="1"/>
      <node ref="U5" pin="2"/>
    </net>
    <net code="96" name="Net-(U5-Pad7)">
      <node ref="U5" pin="7"/>
    </net>
    <net code="97" name="Net-(U5-Pad8)">
      <node ref="U5" pin="8"/>
    </net>
    <net code="98" name="Net-(R13-Pad1)">
      <node ref="U6" pin="5"/>
      <node ref="R13" pin="1"/>
    </net>
    <net code="99" name="Net-(C29-Pad1)">
      <node ref="C29" pin="1"/>
      <node ref="R13" pin="2"/>
      <node ref="NP1" pin="2"/>
      <node ref="NP2" pin="1"/>
    </net>
  </nets>
</export>
